mathtextnlufunc/__init__.py
mathtextnlufunc/sentiment.py
mathtextnlufunc/text2int.py
mathtextnlufunc-0.1.1.dist-info/METADATA
mathtextnlufunc-0.1.1.dist-info/WHEEL
mathtextnlufunc-0.1.1.dist-info/RECORD
