Metadata-Version: 2.1
Name: mathtextnlufunc
Version: 0.1.1
Summary: Mathtext NLU Functions
License: AGPL-3.0
Author: Cetin CAKIR
Author-email: cetincakirtr@gmail.com
Requires-Python: >=3.10,<4.0
Classifier: License :: OSI Approved :: GNU Affero General Public License v3
Classifier: Programming Language :: Python :: 3
Classifier: Programming Language :: Python :: 3.10
Classifier: Programming Language :: Python :: 3.11
Requires-Dist: torch (>=1.13.1,<2.0.0)
Requires-Dist: transformers (>=4.25.1,<5.0.0)
